treadadr/__init__.py
treadadr-0.0.1.dist-info/LICENSE
treadadr-0.0.1.dist-info/METADATA
treadadr-0.0.1.dist-info/WHEEL
treadadr-0.0.1.dist-info/entry_points.txt
treadadr-0.0.1.dist-info/top_level.txt
treadadr-0.0.1.dist-info/RECORD
